fileasy.py
fileasy-0.1.2.dist-info/licenses/LICENSE
fileasy-0.1.2.dist-info/METADATA
fileasy-0.1.2.dist-info/WHEEL
fileasy-0.1.2.dist-info/entry_points.txt
fileasy-0.1.2.dist-info/top_level.txt
fileasy-0.1.2.dist-info/RECORD
