Metadata-Version: 2.4
Name: fileasy
Version: 0.1.2
Summary: Fileasy is a simple CLI tool to convert images to PDFs and vice versa, and merge PDFs
Home-page: https://nazimadda.github.io/fileasy/
Author: Nazim Adda
Author-email: adda.nazim7@gmail.com
License: Apache-2.0
Project-URL: Bug Reports, https://github.com/nazimadda/fileasy/issues
Project-URL: Source, https://github.com/nazimadda  
Keywords: file conversion pdf image merge cli
Platform: Unix
Platform: Windows
Platform: MacOS
Classifier: Development Status :: 3 - Alpha
Classifier: Intended Audience :: Developers
Classifier: Topic :: Software Development :: Build Tools
Classifier: Programming Language :: Python :: 3
Classifier: Programming Language :: Python :: 3.8
Classifier: Programming Language :: Python :: 3.9
Classifier: Environment :: Console
Requires-Python: >=3.7
License-File: LICENSE
Requires-Dist: pdf2image>=1.17.0
Requires-Dist: pillow>=9.0.0
Requires-Dist: PyPDF2>=3.0.0
Dynamic: author
Dynamic: author-email
Dynamic: classifier
Dynamic: description
Dynamic: description-content-type
Dynamic: home-page
Dynamic: keywords
Dynamic: license
Dynamic: license-file
Dynamic: platform
Dynamic: project-url
Dynamic: requires-dist
Dynamic: requires-python
Dynamic: summary
